thisthat/__init__.py
thisthat/file.py
thisthat/line.py
thisthat/module.py
thisthat/package.py
thisthat/source.py
thisthat-0.0.1.dist-info/LICENSE
thisthat-0.0.1.dist-info/METADATA
thisthat-0.0.1.dist-info/WHEEL
thisthat-0.0.1.dist-info/top_level.txt
thisthat-0.0.1.dist-info/RECORD
