Metadata-Version: 2.1
Name: thisthat
Version: 0.0.1
Summary: Reflection/inspection utilities.
Author-email: Piotr Mardziel <piotrm@gmail.com>
Project-URL: Homepage, https://github.com/piotrm0/this
Project-URL: Bug Tracker, https://github.com/piotrm0/this/issues
Classifier: Programming Language :: Python :: 3
Classifier: License :: OSI Approved :: Artistic License
Classifier: Operating System :: OS Independent
Requires-Python: >=3.7
License-File: LICENSE
